alerce/__init__.py
alerce/core.py
alerce/crossmatch.py
alerce/direct.py
alerce/exceptions.py
alerce/search.py
alerce/stamps.py
alerce/utils.py
alerce-1.4.0.dist-info/LICENSE.txt
alerce-1.4.0.dist-info/METADATA
alerce-1.4.0.dist-info/WHEEL
alerce-1.4.0.dist-info/top_level.txt
alerce-1.4.0.dist-info/RECORD
