Metadata-Version: 2.1
Name: alerce
Version: 1.4.0
Summary: ALeRCE Client
Author: ALeRCE Team
Author-email: contact@alerce.online
License-File: LICENSE.txt
Requires-Dist: pandas>=1.1.2
Requires-Dist: astropy>=4.0.1
Requires-Dist: requests>=2.24.0
